superjwt/__init__.py
superjwt/_version.py
superjwt/algorithms.py
superjwt/exceptions.py
superjwt/jws.py
superjwt/jwt.py
superjwt/keys.py
superjwt/utils.py
superjwt/validations.py
superjwt-0.7.0.dist-info/licenses/LICENSE
superjwt-0.7.0.dist-info/METADATA
superjwt-0.7.0.dist-info/WHEEL
superjwt-0.7.0.dist-info/top_level.txt
superjwt-0.7.0.dist-info/RECORD
