Metadata-Version: 2.4
Name: superjwt
Version: 0.7.0
Summary: A super simple JWT library for Python
Author-email: ixunio <ixunio.dev@gmail.com>
License-Expression: MIT
Project-URL: Homepage, https://github.com/ixunio/superjwt
Project-URL: Repository, https://github.com/ixunio/superjwt.git
Project-URL: Changelog, https://github.com/ixunio/superjwt/blob/main/CHANGELOG.md
Keywords: jwt,json,web,token,security,authentication,authorization,auth,oauth,bearer,jose,pydantic
Classifier: Development Status :: 5 - Production/Stable
Classifier: Intended Audience :: Developers
Classifier: Programming Language :: Python :: 3
Classifier: Programming Language :: Python :: 3 :: Only
Classifier: Programming Language :: Python :: 3.10
Classifier: Programming Language :: Python :: 3.11
Classifier: Programming Language :: Python :: 3.12
Classifier: Programming Language :: Python :: 3.13
Classifier: Programming Language :: Python :: 3.14
Classifier: Topic :: Internet :: WWW/HTTP
Classifier: Topic :: Security
Requires-Python: >=3.10
License-File: LICENSE
Requires-Dist: pydantic>=2
Requires-Dist: typing-extensions>=4.0.1
Provides-Extra: asymmetric
Requires-Dist: cryptography>=43.0.0; extra == "asymmetric"
Dynamic: license-file
